LICENSE
MANIFEST.in
README.md
VERSION
setup.py
aep_site/__init__.py
aep_site/cli.py
aep_site/md.py
aep_site/publisher.py
aep_site/server.py
aep_site/utils.py
aep_site/jinja/__init__.py
aep_site/jinja/env.py
aep_site/jinja/loaders.py
aep_site/jinja/ext/__init__.py
aep_site/jinja/ext/sample.py
aep_site/jinja/ext/tab.py
aep_site/models/__init__.py
aep_site/models/aep.py
aep_site/models/page.py
aep_site/models/scope.py
aep_site/models/site.py
aep_site/support/assets/favicon.ico
aep_site/support/assets/images/aep.svg
aep_site/support/assets/images/github.png
aep_site/support/assets/images/glue-icons.svg
aep_site/support/assets/js/global.js
aep_site/support/assets/js/syntax.js
aep_site/support/assets/js/aep/aep-graphviz.js
aep_site/support/assets/js/aep/aep-index.js
aep_site/support/assets/js/graphviz/lite.render.js
aep_site/support/assets/js/graphviz/viz.js
aep_site/support/assets/js/search/pagination.js
aep_site/support/assets/js/search/tipuesearch.min.js
aep_site/support/assets/js/search/tipuesearch_set.js
aep_site/support/assets/misc/ebnf-filtering.txt
aep_site/support/scss/hero.scss
aep_site/support/scss/print.scss
aep_site/support/scss/search.scss
aep_site/support/scss/style.scss
aep_site/support/scss/imports/callouts.scss
aep_site/support/scss/imports/colors.scss
aep_site/support/scss/imports/footer.scss
aep_site/support/scss/imports/header.scss
aep_site/support/scss/imports/headings.scss
aep_site/support/scss/imports/lists.scss
aep_site/support/scss/imports/nav.scss
aep_site/support/scss/imports/sidebar.scss
aep_site/support/scss/imports/syntax.scss
aep_site/support/scss/imports/tables.scss
aep_site/support/scss/imports/tabs.scss
aep_site/support/scss/imports/aep/badges.scss
aep_site/support/scss/imports/aep/breadcrumbs.scss
aep_site/support/scss/imports/aep/header.scss
aep_site/support/scss/imports/aep/nav.scss
aep_site/support/scss/imports/aep/news.scss
aep_site/support/scss/imports/aep/tables.scss
aep_site/support/templates/aep-listing.html.j2
aep_site_generator.egg-info/PKG-INFO
aep_site_generator.egg-info/SOURCES.txt
aep_site_generator.egg-info/dependency_links.txt
aep_site_generator.egg-info/entry_points.txt
aep_site_generator.egg-info/not-zip-safe
aep_site_generator.egg-info/requires.txt
aep_site_generator.egg-info/top_level.txt