Metadata-Version: 2.1
Name: aep-site-generator
Version: 0.9.1
Summary: Static site generator for aep.dev and forks.
Home-page: https://github.com/aep-dev/site-generator.git
Author: Luke Sneeringer
Author-email: lukesneeringer@google.com
License: Apache 2.0
Platform: Posix; MacOS X
Classifier: Development Status :: 4 - Beta
Classifier: Environment :: Console
Classifier: Intended Audience :: Developers
Classifier: License :: OSI Approved :: Apache Software License
Classifier: Operating System :: POSIX
Classifier: Programming Language :: Python :: 3.8
Classifier: Topic :: Software Development :: Code Generators
Requires-Python: >=3.8
License-File: LICENSE
